ya2ro/__init__.py
ya2ro/data_wrapper.py
ya2ro/hilite_me.py
ya2ro/htaccess.py
ya2ro/properties.py
ya2ro/req_doi.py
ya2ro/req_orcid.py
ya2ro/ro_html.py
ya2ro/ro_jsonld.py
ya2ro/ro_landing_page.py
ya2ro/ya2ro.py
ya2ro/images/complete_paper.png
ya2ro/images/default_author.jpg
ya2ro/resources/help.html
ya2ro/resources/input_to_vocab.yaml
ya2ro/resources/landing_page.html
ya2ro/resources/properties.yaml
ya2ro/resources/template.html
ya2ro-0.0.4.dist-info/LICENSE
ya2ro-0.0.4.dist-info/METADATA
ya2ro-0.0.4.dist-info/WHEEL
ya2ro-0.0.4.dist-info/entry_points.txt
ya2ro-0.0.4.dist-info/top_level.txt
ya2ro-0.0.4.dist-info/RECORD
