Metadata-Version: 2.1
Name: ya2ro
Version: 0.0.4
Summary: Tool to which you pass basic information of a project or a research article (such as the datasets, software, people who have been involved, bibliography...) and generates two files with structured information with the intention of easing the readability for machines and people. One file is a webpage with all the relevant information and the other one is a Research Object.
Home-page: https://github.com/oeg-upm/ya2ro
Author: Antonia Pavel, Daniel Garijo
Author-email: daniel.garijo@upm.es
License: Apache License 2.0
License-File: LICENSE
Requires-Dist: PyYAML (>=5.0.0)
Requires-Dist: bs4 (>=0.0.1)
Requires-Dist: requests (>=2.22.0)
Requires-Dist: bibtexparser (>=1.2.0)
Requires-Dist: Pygments (>=2.11.2)
Requires-Dist: somef (>=0.9.3)
Requires-Dist: soca (>=0.0.1)
Requires-Dist: metadata-parser
